tracebloc_ingestor/__init__.py
tracebloc_ingestor/config.py
tracebloc_ingestor/database.py
tracebloc_ingestor/file_transfer.py
tracebloc_ingestor/api/__init__.py
tracebloc_ingestor/api/client.py
tracebloc_ingestor/ingestors/__init__.py
tracebloc_ingestor/ingestors/base.py
tracebloc_ingestor/ingestors/csv_ingestor.py
tracebloc_ingestor/ingestors/json_ingestor.py
tracebloc_ingestor/utils/__init__.py
tracebloc_ingestor/utils/constants.py
tracebloc_ingestor/utils/logging.py
tracebloc_ingestor/utils/validators_mapping.py
tracebloc_ingestor/validators/__init__.py
tracebloc_ingestor/validators/base.py
tracebloc_ingestor/validators/data_validator.py
tracebloc_ingestor/validators/duplicate_validator.py
tracebloc_ingestor/validators/file_validator.py
tracebloc_ingestor/validators/image_validator.py
tracebloc_ingestor/validators/table_name_validator.py
tracebloc_ingestor/validators/time_series_validator.py
tracebloc_ingestor/validators/xml_validator.py
tracebloc_ingestor-0.2.7.dist-info/licenses/LICENSE
tracebloc_ingestor-0.2.7.dist-info/METADATA
tracebloc_ingestor-0.2.7.dist-info/WHEEL
tracebloc_ingestor-0.2.7.dist-info/top_level.txt
tracebloc_ingestor-0.2.7.dist-info/RECORD
